stellrent_response/__init__.py
stellrent_response/json_response.py
stellrent_response-1.3.0.dist-info/licenses/LICENSE
stellrent_response-1.3.0.dist-info/METADATA
stellrent_response-1.3.0.dist-info/WHEEL
stellrent_response-1.3.0.dist-info/top_level.txt
stellrent_response-1.3.0.dist-info/RECORD
