Metadata-Version: 2.4
Name: stellrent_response
Version: 1.3.0
Author: Marcus R. Magalhães
Author-email: Marcus Rodrigues Magalhães <marcusrodrigues.magalhaes@stellantis.com>
Project-URL: Homepage, https://github.com/stellrent/stellrent-response
Project-URL: Issues, https://github.com/stellrent/stellrent-response/issues
Classifier: Development Status :: 5 - Production/Stable
Classifier: Environment :: Web Environment
Classifier: Intended Audience :: Developers
Classifier: Natural Language :: English
Classifier: Programming Language :: Python
Classifier: Programming Language :: Python :: 3
Classifier: Programming Language :: Python :: 3.9
Classifier: Programming Language :: Python :: 3.10
Classifier: Programming Language :: Python :: 3.11
Classifier: License :: OSI Approved :: MIT License
Classifier: Operating System :: OS Independent
Classifier: Framework :: Flask
Classifier: Topic :: Internet :: WWW/HTTP
Requires-Python: >=3.9
License-File: LICENSE
Dynamic: author
Dynamic: license-file
